lsyflaskmicroapp_fstore/__init__.py
lsyflaskmicroapp_fstore/orm.py
lsyflaskmicroapp_fstore/apis/__init__.py
lsyflaskmicroapp_fstore/apis/store_file.py
lsyflaskmicroapp_fstore/apis/store_folder.py
lsyflaskmicroapp_fstore/entitys/__init__.py
lsyflaskmicroapp_fstore/entitys/store_file.py
lsyflaskmicroapp_fstore/entitys/store_folder.py
lsyflaskmicroapp_fstore/models/__init__.py
lsyflaskmicroapp_fstore/models/store_file.py
lsyflaskmicroapp_fstore/models/store_folder.py
lsyflaskmicroapp_fstore/schemas/__init__.py
lsyflaskmicroapp_fstore/schemas/store_file.py
lsyflaskmicroapp_fstore/schemas/store_folder.py
lsyflaskmicroapp_fstore-1.0.0.dist-info/METADATA
lsyflaskmicroapp_fstore-1.0.0.dist-info/WHEEL
lsyflaskmicroapp_fstore-1.0.0.dist-info/top_level.txt
lsyflaskmicroapp_fstore-1.0.0.dist-info/RECORD
